effulge/__init__.py
effulge/effulge.py
effulge/report_generator.py
effulge/scatter_tree_compare.py
effulge/scatter_tree_nodes.py
Effulge-0.0.1.dist-info/LICENSE
Effulge-0.0.1.dist-info/METADATA
Effulge-0.0.1.dist-info/WHEEL
Effulge-0.0.1.dist-info/top_level.txt
Effulge-0.0.1.dist-info/RECORD
