Metadata-Version: 2.1
Name: Effulge
Version: 0.0.1
Summary: A small package used to find data variances
Home-page: https://github.com/Regish/Effulge
Author: Regish
Author-email: regishdhanush@gmail.com
Project-URL: Bug Tracker, https://github.com/Regish/Effulge/issues
Classifier: Programming Language :: Python :: 3
Classifier: License :: OSI Approved :: MIT License
Classifier: Operating System :: OS Independent
Requires-Python: >=3.0
License-File: LICENSE
Requires-Dist: pyspark (>=3.0.0)
Requires-Dist: pandas (>=1.3.0)
Requires-Dist: XlsxWriter (>=3.0.3)
